{
    "Objects": [
        {
            "Type": "nap::ArtNetController",
            "mID": "ArtNetController",
            "Subnet": 0,
            "Universe": 0,
            "IPAddress": "",
            "WaitTime": 2.0,
            "Frequency": 44,
            "Mode": "Broadcast",
            "UnicastLimit": 10,
            "Verbose": false,
            "Timeout": 2.0
        },
        {
            "Type": "nap::RenderWindow",
            "mID": "Window",
            "Borderless": false,
            "Resizable": true,
            "Visible": true,
            "SampleShading": true,
            "Title": "ArtNet Sending Demo",
            "Width": 1280,
            "Height": 720,
            "Mode": "Immediate",
            "ClearColor": {
                "Values": [
                    0.0,
                    0.0,
                    0.0,
                    1.0
                ]
            },
            "Samples": "Four",
            "AdditionalSwapImages": 1
        },
        {
            "Type": "nap::Scene",
            "mID": "Scene",
            "Entities": []
        }
    ]
}