{
    "Objects": [
        {
            "Type": "nap::ComputeMaterial",
            "mID": "ComputeMaterial",
            "Uniforms": [],
            "StorageUniforms": [
                {
                    "Type": "nap::StorageUniformStruct",
                    "mID": "StorageUniformStruct_afd17387",
                    "Name": "VertexBuffer",
                    "StorageUniform": {
                        "Type": "nap::StorageUniformVec4Buffer",
                        "mID": "StorageUniformVec4Buffer_970dc79d",
                        "Name": "vertices",
                        "Buffer": "GPUVec4Buffer_Vertices"
                    }
                }
            ],
            "Samplers": [],
            "Shader": "ComputeShader"
        },
        {
            "Type": "nap::ComputeShaderFromFile",
            "mID": "ComputeShader",
            "ComputeShader": "shaders/update.comp"
        },
        {
            "Type": "nap::Entity",
            "mID": "CameraEntity",
            "Components": [
                {
                    "Type": "nap::PerspCameraComponent",
                    "mID": "PerspCameraComponent",
                    "Properties": {
                        "FieldOfView": 55.0,
                        "NearClippingPlane": 0.009999999776482582,
                        "FarClippingPlane": 1000.0,
                        "GridDimensions": {
                            "x": 1,
                            "y": 1
                        },
                        "GridLocation": {
                            "x": 0,
                            "y": 0
                        }
                    }
                },
                {
                    "Type": "nap::KeyInputComponent",
                    "mID": "nap::KeyInputComponent"
                },
                {
                    "Type": "nap::PointerInputComponent",
                    "mID": "nap::PointerInputComponent"
                },
                {
                    "Type": "nap::FirstPersonController",
                    "mID": "nap::FirstPersonController",
                    "MovementSpeed": 2.0,
                    "RotateSpeed": 0.0020000000949949028,
                    "PerspCameraComponent": "PerspCameraComponent"
                },
                {
                    "Type": "nap::TransformComponent",
                    "mID": "nap::TransformComponent",
                    "Properties": {
                        "Translate": {
                            "x": 0.0,
                            "y": -0.5,
                            "z": 3.5
                        },
                        "Rotate": {
                            "x": 50.0,
                            "y": 0.0,
                            "z": 0.0
                        },
                        "Scale": {
                            "x": 1.0,
                            "y": 1.0,
                            "z": 1.0
                        },
                        "UniformScale": 1.0
                    }
                }
            ],
            "Children": []
        },
        {
            "Type": "nap::Entity",
            "mID": "DefaultInputRouterEntity",
            "Components": [
                {
                    "Type": "nap::DefaultInputRouterComponent",
                    "mID": "nap::DefaultInputRouterComponent"
                }
            ],
            "Children": []
        },
        {
            "Type": "nap::Entity",
            "mID": "ParticleVolumeEntity",
            "Components": [
                {
                    "Type": "nap::ParticleVolumeComponent",
                    "mID": "ParticleVolumeComponent",
                    "Visible": true,
                    "Mesh": "",
                    "MaterialInstance": {
                        "Material": "ParticleMaterial",
                        "Uniforms": [],
                        "StorageUniforms": [],
                        "Samplers": [],
                        "BlendMode": "NotSet",
                        "DepthMode": "NotSet"
                    },
                    "LineWidth": 1.0,
                    "ClipRect": {
                        "Min": {
                            "x": 0.0,
                            "y": 0.0
                        },
                        "Max": {
                            "x": 0.0,
                            "y": 0.0
                        }
                    },
                    "NumParticles": 1000,
                    "Size": 0.03999999910593033,
                    "RotationSpeed": 0.5,
                    "Velocity": 0.5,
                    "VelocityVariation": 0.75
                },
                {
                    "Type": "nap::TransformComponent",
                    "mID": "nap::TransformComponent_2",
                    "Properties": {
                        "Translate": {
                            "x": 0.0,
                            "y": 0.0,
                            "z": 0.0
                        },
                        "Rotate": {
                            "x": 0.0,
                            "y": 0.0,
                            "z": 0.0
                        },
                        "Scale": {
                            "x": 1.0,
                            "y": 1.0,
                            "z": 1.0
                        },
                        "UniformScale": 1.0
                    }
                },
                {
                    "Type": "nap::ComputeComponent",
                    "mID": "ComputeComponent_A",
                    "ComputeMaterialInstance": {
                        "ComputeMaterial": "ComputeMaterial",
                        "Uniforms": [],
                        "StorageUniforms": [
                            {
                                "Type": "nap::StorageUniformStruct",
                                "mID": "StorageUniformStruct_0fa64241",
                                "Name": "ParticleBuffer_In",
                                "StorageUniform": {
                                    "Type": "nap::StorageUniformStructBuffer",
                                    "mID": "StorageUniformStructBuffer_2f2aafc2",
                                    "Name": "particles",
                                    "Buffer": "GPUStructBuffer_Particles"
                                }
                            },
                            {
                                "Type": "nap::StorageUniformStruct",
                                "mID": "StorageUniformStruct_406bb963",
                                "Name": "ParticleBuffer_Out",
                                "StorageUniform": {
                                    "Type": "nap::StorageUniformStructBuffer",
                                    "mID": "StorageUniformStructBuffer_80e8d81c",
                                    "Name": "particles",
                                    "Buffer": "GPUStructBuffer_Particles2"
                                }
                            }
                        ],
                        "Samplers": []
                    }
                },
                {
                    "Type": "nap::ComputeComponent",
                    "mID": "ComputeComponent_B",
                    "ComputeMaterialInstance": {
                        "ComputeMaterial": "ComputeMaterial",
                        "Uniforms": [],
                        "StorageUniforms": [
                            {
                                "Type": "nap::StorageUniformStruct",
                                "mID": "StorageUniformStruct_30fe19c9",
                                "Name": "ParticleBuffer_In",
                                "StorageUniform": {
                                    "Type": "nap::StorageUniformStructBuffer",
                                    "mID": "StorageUniformStructBuffer_b40f779b",
                                    "Name": "particles",
                                    "Buffer": "GPUStructBuffer_Particles2"
                                }
                            },
                            {
                                "Type": "nap::StorageUniformStruct",
                                "mID": "StorageUniformStruct_85c16027",
                                "Name": "ParticleBuffer_Out",
                                "StorageUniform": {
                                    "Type": "nap::StorageUniformStructBuffer",
                                    "mID": "StorageUniformStructBuffer_00e07917",
                                    "Name": "particles",
                                    "Buffer": "GPUStructBuffer_Particles"
                                }
                            }
                        ],
                        "Samplers": []
                    }
                }
            ],
            "Children": []
        },
        {
            "Type": "nap::GPUStructBuffer",
            "mID": "GPUStructBuffer_Particles",
            "Descriptor": {
                "Element": {
                    "Type": "nap::UniformStruct",
                    "mID": "UniformStruct_45f9fab3",
                    "Name": "particles",
                    "Uniforms": [
                        {
                            "Type": "nap::UniformVec4",
                            "mID": "UniformVec4_7ac6f70b",
                            "Name": "position",
                            "Value": {
                                "x": 0.0,
                                "y": 0.0,
                                "z": 0.0,
                                "w": 0.0
                            }
                        },
                        {
                            "Type": "nap::UniformVec4",
                            "mID": "UniformVec4_a02e4adb",
                            "Name": "velocity",
                            "Value": {
                                "x": 0.0,
                                "y": 0.0,
                                "z": 0.0,
                                "w": 0.0
                            }
                        },
                        {
                            "Type": "nap::UniformVec4",
                            "mID": "UniformVec4_0816be02",
                            "Name": "rotation",
                            "Value": {
                                "x": 0.0,
                                "y": 0.0,
                                "z": 0.0,
                                "w": 0.0
                            }
                        },
                        {
                            "Type": "nap::UniformVec4",
                            "mID": "UniformVec4_e7ee127a",
                            "Name": "color",
                            "Value": {
                                "x": 0.0,
                                "y": 0.0,
                                "z": 0.0,
                                "w": 0.0
                            }
                        }
                    ]
                },
                "Count": 1000
            },
            "Usage": "Static",
            "FillPolicy": {
                "Type": "nap::UniformRandomStructBufferFillPolicy",
                "mID": "UniformRandomStructBufferFillPolicy_49de23bd"
            }
        },
        {
            "Type": "nap::GPUStructBuffer",
            "mID": "GPUStructBuffer_Particles2",
            "Descriptor": {
                "Element": {
                    "Type": "nap::UniformStruct",
                    "mID": "UniformStruct_a35bf039",
                    "Name": "particles",
                    "Uniforms": [
                        {
                            "Type": "nap::UniformVec4",
                            "mID": "UniformVec4_0676c053",
                            "Name": "position",
                            "Value": {
                                "x": 0.0,
                                "y": 0.0,
                                "z": 0.0,
                                "w": 0.0
                            }
                        },
                        {
                            "Type": "nap::UniformVec4",
                            "mID": "UniformVec4_ff103c73",
                            "Name": "velocity",
                            "Value": {
                                "x": 0.0,
                                "y": 0.0,
                                "z": 0.0,
                                "w": 0.0
                            }
                        },
                        {
                            "Type": "nap::UniformVec4",
                            "mID": "UniformVec4_b822b7b5",
                            "Name": "rotation",
                            "Value": {
                                "x": 0.0,
                                "y": 0.0,
                                "z": 0.0,
                                "w": 0.0
                            }
                        },
                        {
                            "Type": "nap::UniformVec4",
                            "mID": "UniformVec4_5c0d40fe",
                            "Name": "color",
                            "Value": {
                                "x": 0.0,
                                "y": 0.0,
                                "z": 0.0,
                                "w": 0.0
                            }
                        }
                    ]
                },
                "Count": 1000
            },
            "Usage": "Static",
            "FillPolicy": ""
        },
        {
            "Type": "nap::GPUVec4Buffer",
            "mID": "GPUVec4Buffer_Positions",
            "Count": 1000000,
            "Usage": "Static",
            "BufferObjectType": "Storage",
            "FillPolicy": ""
        },
        {
            "Type": "nap::GPUVec4Buffer",
            "mID": "GPUVec4Buffer_Positions2",
            "Count": 1000000,
            "Usage": "Static",
            "BufferObjectType": "Storage",
            "FillPolicy": ""
        },
        {
            "Type": "nap::GPUVec4Buffer",
            "mID": "GPUVec4Buffer_Rotations",
            "Count": 1000000,
            "Usage": "Static",
            "BufferObjectType": "Storage",
            "FillPolicy": ""
        },
        {
            "Type": "nap::GPUVec4Buffer",
            "mID": "GPUVec4Buffer_Velocities",
            "Count": 1000000,
            "Usage": "Static",
            "BufferObjectType": "Storage",
            "FillPolicy": ""
        },
        {
            "Type": "nap::GPUVec4Buffer",
            "mID": "GPUVec4Buffer_Vertices",
            "Count": 4000,
            "Usage": "Static",
            "BufferObjectType": "Storage",
            "FillPolicy": ""
        },
        {
            "Type": "nap::ImageFromFile",
            "mID": "ParticleOne",
            "Usage": "Static",
            "ImagePath": "texture_one.jpg",
            "GenerateLods": true
        },
        {
            "Type": "nap::ImageFromFile",
            "mID": "ParticleTwo",
            "Usage": "Static",
            "ImagePath": "texture_two.png",
            "GenerateLods": true
        },
        {
            "Type": "nap::Material",
            "mID": "ParticleMaterial",
            "Uniforms": [],
            "StorageUniforms": [],
            "Samplers": [
                {
                    "Type": "nap::Sampler2DArray",
                    "mID": "UniformTexture2DArray_be091041",
                    "Name": "texture_input",
                    "MinFilter": "Linear",
                    "MaxFilter": "Linear",
                    "MipMapMode": "Linear",
                    "AddressModeVertical": "ClampToEdge",
                    "AddressModeHorizontal": "ClampToEdge",
                    "MaxLodLevel": 1000,
                    "AnisotropicSamples": "Default",
                    "Textures": [
                        "ParticleOne",
                        "ParticleTwo"
                    ]
                }
            ],
            "Shader": "ParticleShader",
            "VertexAttributeBindings": [
                {
                    "MeshAttributeID": "Position",
                    "ShaderAttributeID": "in_Position"
                },
                {
                    "MeshAttributeID": "UV0",
                    "ShaderAttributeID": "in_UV0"
                },
                {
                    "MeshAttributeID": "Id",
                    "ShaderAttributeID": "in_Id"
                }
            ],
            "BlendMode": "AlphaBlend",
            "DepthMode": "ReadWrite"
        },
        {
            "Type": "nap::RenderWindow",
            "mID": "Window0",
            "Borderless": false,
            "Resizable": true,
            "Visible": true,
            "SampleShading": true,
            "Title": "ComputeParticlesDemo",
            "Width": 1280,
            "Height": 720,
            "Mode": "Immediate",
            "ClearColor": {
                "Values": [
                    0.06700000166893006,
                    0.07800000160932541,
                    0.14900000393390656,
                    1.0
                ]
            },
            "Samples": "Four",
            "AdditionalSwapImages": 1
        },
        {
            "Type": "nap::Scene",
            "mID": "Scene",
            "Entities": [
                {
                    "Entity": "CameraEntity",
                    "InstanceProperties": []
                },
                {
                    "Entity": "DefaultInputRouterEntity",
                    "InstanceProperties": []
                },
                {
                    "Entity": "ParticleVolumeEntity",
                    "InstanceProperties": []
                }
            ]
        },
        {
            "Type": "nap::ShaderFromFile",
            "mID": "ParticleShader",
            "VertShader": "shaders/particle.vert",
            "FragShader": "shaders/particle.frag"
        }
    ]
}